README.md
setup.py
pyrequestsv2/__init__.py
pyrequestsv2.egg-info/PKG-INFO
pyrequestsv2.egg-info/SOURCES.txt
pyrequestsv2.egg-info/dependency_links.txt
pyrequestsv2.egg-info/requires.txt
pyrequestsv2.egg-info/top_level.txt